{
  "intList": {},
  "doubList": {
    "widthm": 2.5,
    "zoomLevel": 0.5,
    "heightm": 9.0
  },
  "collPointList": [
    {
      "x": -1.25,
      "y": -4.54
    },
    {
      "x": -1.19,
      "y": -1.72
    },
    {
      "x": -1.27,
      "y": 0.38
    },
    {
      "x": -1.23,
      "y": 1.38
    },
    {
      "x": -0.19,
      "y": 1.5
    },
    {
      "x": 0.03,
      "y": 3.54
    },
    {
      "x": 1.17,
      "y": 3.62
    },
    {
      "x": 1.09,
      "y": -4.52
    }
  ],
  "floatList": {},
  "strList": {},
  "boolList": {}
}