{"levelEndX":14.96,"polygonCollision":true,"levelEndY":13.65,"boulders":[],"nextLevelName":"nextLevel","levelName":"Ramp","boulderJoints":[],"respawnPoints":[],"platforms":[{"centerY":13.36,"imageName":"Ramp.png","centerX":2.7,"moveable":false,"imageSizeHeight":10.0,"scale":1.0,"velocity":1.0,"imageSizeWidth":15.0,"disappears":false,"collidable":true,"collisionPoints":[{"x":-7.3,"y":-4.8},{"x":7.1,"y":4.4},{"x":6.7,"y":-5.4}],"springCK":1.0,"endY":0.0,"endX":0.0,"sinkable":false,"climbable":false},{"centerY":6.642857142857142,"imageName":"arEast.png","centerX":-9.771428571428572,"moveable":false,"imageSizeHeight":3.0,"scale":1.0,"velocity":1.0,"imageSizeWidth":15.0,"disappears":false,"collidable":true,"collisionPoints":[{"x":-7.42,"y":-1.54},{"x":-7.46,"y":1.42},{"x":7.46,"y":1.38},{"x":7.5,"y":-1.58}],"springCK":1.0,"endY":0.0,"endX":0.0,"sinkable":false,"climbable":false}],"mToPixel":35.0,"characters":{"Monkey":{"startingXPos":1.55,"startingYPos":14.34,"present":true},"Piggy":{"startingXPos":0.0,"startingYPos":0.0,"present":false},"Sandy":{"startingXPos":0.0,"startingYPos":0.0,"present":false},"Monk":{"startingXPos":0.0,"startingYPos":0.0,"present":false}},"attackZones":[],"background":{"imageName":"bgSunny.png","width":20.0,"height":15.0},"vines":[],"goldenPegs":[]}